mkdocs_render_stopper/__init__.py
mkdocs_render_stopper/plugin.py
mkdocs_render_stopper-0.1.1.dist-info/LICENSE
mkdocs_render_stopper-0.1.1.dist-info/METADATA
mkdocs_render_stopper-0.1.1.dist-info/WHEEL
mkdocs_render_stopper-0.1.1.dist-info/entry_points.txt
mkdocs_render_stopper-0.1.1.dist-info/top_level.txt
mkdocs_render_stopper-0.1.1.dist-info/RECORD
