Metadata-Version: 2.1
Name: mkdocs-render-stopper
Version: 0.1.1
Summary: A MkDocs plugin to stop rendering at a specific tag.
Home-page: https://github.com/jfcmontmorency/mkdocs-render-stopper
Author: Jean-François Cartier
Author-email: jfcartier@cmontmorency.qc.ca
License: MIT
Classifier: Development Status :: 4 - Beta
Classifier: Intended Audience :: Developers
Classifier: License :: OSI Approved :: MIT License
Classifier: Programming Language :: Python :: 3
Classifier: Programming Language :: Python :: 3.6
Classifier: Programming Language :: Python :: 3.7
Classifier: Programming Language :: Python :: 3.8
Classifier: Programming Language :: Python :: 3.9
Classifier: Programming Language :: Python :: 3.10
Classifier: Framework :: MkDocs
Requires-Python: >=3.6
License-File: LICENSE
Requires-Dist: mkdocs >=1.4.2
Requires-Dist: lxml >=4.7.0
